turbotutils/__init__.py
turbotutils/account.py
turbotutils/billing.py
turbotutils/cluster.py
turbotutils/guardrails.py
turbotutils/network.py
turbotutils/notifications.py
turbotutils-0.2.0.dist-info/METADATA
turbotutils-0.2.0.dist-info/RECORD
turbotutils-0.2.0.dist-info/WHEEL
turbotutils-0.2.0.dist-info/top_level.txt
