Metadata-Version: 2.1
Name: turbotutils
Version: 0.2.0
Summary: TurbotHQ API Library
Home-page: https://github.com/mosburn/turbot_utils
Author: Michael Osburn <michael@mosburn.com>
Author-email: michael@mosburn.com
License: UNKNOWN
Keywords: Turbot
Platform: UNKNOWN
Classifier: Development Status :: 3 - Alpha
Classifier: Intended Audience :: Information Technology
Classifier: License :: OSI Approved :: GNU General Public License v2 (GPLv2)
Classifier: Natural Language :: English
Classifier: Operating System :: OS Independent
Classifier: Programming Language :: Python :: 3
Classifier: Topic :: Software Development :: Libraries :: Application Frameworks
Requires-Dist: requests
Requires-Dist: configparser
